ra/__init__.py
ra/ra.py
raViz-0.1.0.dist-info/LICENSE
raViz-0.1.0.dist-info/METADATA
raViz-0.1.0.dist-info/WHEEL
raViz-0.1.0.dist-info/top_level.txt
raViz-0.1.0.dist-info/RECORD
