Metadata-Version: 2.1
Name: raViz
Version: 0.1.0
Summary: Package to help create flow visualizations
Home-page: https://github.com/utepnetlab/ra
Author: Christopher Mendoza
Author-email: camendoza7@miners.utep.edu
License: UNKNOWN
Platform: UNKNOWN
Classifier: Programming Language :: Python :: 3
Classifier: License :: OSI Approved :: MIT License
Classifier: Operating System :: OS Independent
